zwt5/1.txt
zwt5/__init__.py
zwt5/add.py
zwt5/division.py
zwt5/multiply.py
zwt5/subtract.py
zwt5/adv/__init__.py
zwt5/adv/sqrt.py
zwt5-0.1.15.dist-info/METADATA
zwt5-0.1.15.dist-info/WHEEL
zwt5-0.1.15.dist-info/top_level.txt
zwt5-0.1.15.dist-info/RECORD
